odinweb/__init__.py
odinweb/bottle.py
odinweb.bottle-0.5.0.dist-info/DESCRIPTION.rst
odinweb.bottle-0.5.0.dist-info/METADATA
odinweb.bottle-0.5.0.dist-info/RECORD
odinweb.bottle-0.5.0.dist-info/WHEEL
odinweb.bottle-0.5.0.dist-info/metadata.json
odinweb.bottle-0.5.0.dist-info/pbr.json
odinweb.bottle-0.5.0.dist-info/top_level.txt
