Metadata-Version: 2.0
Name: odinweb.bottle
Version: 0.5.0
Summary: Toolkit for building web API's using Odin and Bottle.
Home-page: https://github.com/python-odin/odinweb.bottle
Author: Tim Savage
Author-email: tim@savage.company
License: BSD
Keywords: web
Requires-Dist: odinweb (>=0.5)
Requires-Dist: bottle
